messi/__init__.py
messi/__main__.py
messi/generate.py
messi/version.py
messi/c_source/__init__.py
messi/c_source/templates/async/client.c
messi/c_source/templates/async/client.h
messi/c_source/templates/async/server.c
messi/c_source/templates/async/server.h
messi/c_source/templates/linux/client.c
messi/c_source/templates/linux/client.h
messi/c_source/templates/linux/server.c
messi/c_source/templates/linux/server.h
messi/py_source/__init__.py
messi/py_source/templates/client.py
messi-0.29.0.dist-info/LICENSE
messi-0.29.0.dist-info/METADATA
messi-0.29.0.dist-info/WHEEL
messi-0.29.0.dist-info/entry_points.txt
messi-0.29.0.dist-info/top_level.txt
messi-0.29.0.dist-info/RECORD
