Metadata-Version: 2.1
Name: messi
Version: 0.29.0
Summary: Reliable message passing in distributed systems.
Home-page: https://github.com/eerimoq/messi
Author: Erik Moqvist
Author-email: erik.moqvist@gmail.com
License: MIT
Platform: UNKNOWN
Classifier: License :: OSI Approved :: MIT License
Classifier: Programming Language :: Python :: 3
Requires-Dist: pbtools
Requires-Dist: bitstruct
Requires-Dist: grpcio-tools
